{
  "BOSS需求解决方案-BOSS-PQ-2019-05-183-fss-新增网络安全增值业务：DNS防护产品开通页面": {
      "FEE_ITEM_BLOCK": [
        {
          "FEE_ITEM": {
            "FEE_ITEM_ID": "88002512",
            "ITEM_NAME": "DNS监测包月费",
            "ACCP_ITEM_TAX_RATE": {
                  "TAX_RATE": "600"
            },
            "ACC_DEF_FEE_ITEM_EX": {
              "MARKET_TYPE_ID": "030",
              "MARKET_TYPE_NAME": "集客"
            },
            "BS_ACCT_ITEM_TYPE": {
              "BILL_PRIORITY": "143"
            },
            "BS_FEE_ITEM_BILL_ITEM_1": {
              "BILL_ITEM_ID": "237"
            },
            "BS_FEE_ITEM_BILL_ITEM_999": {
              "BILL_ITEM_ID": "237"
            },
            "BS_FEE_ITEM_BILL_ITEM_998": {
              "BILL_ITEM_ID": "319"
            },
            "BS_FEE_ITEM_BILL_ITEM_888": {
              "BILL_ITEM_ID": "66666666"
            },
            "BS_FEE_ITEM_BILL_ITEM_21": {},
            "BS_FEE_ITEM_BILL_ITEM_997": {}
          }
        },
        {
          "FEE_ITEM": {
            "FEE_ITEM_ID": "88002513",
            "ITEM_NAME": "DNS强制解析包月费",
            "ACCP_ITEM_TAX_RATE": {
                  "TAX_RATE": "600"
            },
            "ACC_DEF_FEE_ITEM_EX": {
              "MARKET_TYPE_ID": "030",
              "MARKET_TYPE_NAME": "集客"
            },
            "BS_ACCT_ITEM_TYPE": {
              "BILL_PRIORITY": "143"
            },
            "BS_FEE_ITEM_BILL_ITEM_1": {
              "BILL_ITEM_ID": "237"
            },
            "BS_FEE_ITEM_BILL_ITEM_999": {
              "BILL_ITEM_ID": "237"
            },
            "BS_FEE_ITEM_BILL_ITEM_998": {
              "BILL_ITEM_ID": "319"
            },
            "BS_FEE_ITEM_BILL_ITEM_888": {
              "BILL_ITEM_ID": "66666666"
            },
            "BS_FEE_ITEM_BILL_ITEM_21": {},
            "BS_FEE_ITEM_BILL_ITEM_997": {}
          }
        }
      ]
   }
}
