{
  "BOSS需求解决方案-BOSS-PQ-2019-05-093-bichunliang_积分兑换语音、流量及短彩信包": {
      "ALARM_PROD_BLOCK": [
        {
          "ALARM_PROD_HEAD": {
            "PROD_ID": "50002357",
            "PROD_NAME": "积分兑换150分钟国内主叫通话时长",
            "PACKAGE_ALARM_PROD": [
              {
                "ALARM_TYPE": "1"
              },
              {
                "ALARM_TYPE": "4"
              },
              {
                "ALARM_TYPE": "5"
              },
              {
                "ALARM_TYPE": "15"
              }
            ]
          }
        },
        {
          "ALARM_PROD_HEAD": {
            "PROD_ID": "50005460",
            "PROD_NAME": "积分兑换200条短信包",
            "PACKAGE_ALARM_PROD": [
              {
                "ALARM_TYPE": "1"
              },
              {
                "ALARM_TYPE": "4"
              },
              {
                "ALARM_TYPE": "5"
              },
              {
                "ALARM_TYPE": "15"
              }
            ]
          }
        }
      ]
   }
}
